lls_pkg/CoordinateSystem.py
lls_pkg/LLS.py
lls_pkg/NCR.py
lls_pkg/RadioPropagation.py
lls_pkg/__init__.py
lls_pkg_gotodiela-0.0.1.dist-info/LICENSE
lls_pkg_gotodiela-0.0.1.dist-info/METADATA
lls_pkg_gotodiela-0.0.1.dist-info/WHEEL
lls_pkg_gotodiela-0.0.1.dist-info/top_level.txt
lls_pkg_gotodiela-0.0.1.dist-info/RECORD
