Metadata-Version: 2.1
Name: lls-pkg-gotodiela
Version: 0.0.1
Summary: A package for localization
Home-page: https://github.com/pypa/sampleproject
Author: lls
Author-email: null@null.com
License: UNKNOWN
Platform: UNKNOWN
Classifier: Programming Language :: Python :: 3
Classifier: License :: OSI Approved :: MIT License
Classifier: Operating System :: OS Independent
